sourmash_plugin_venn.py
sourmash_plugin_venn-0.5.dist-info/LICENSE
sourmash_plugin_venn-0.5.dist-info/METADATA
sourmash_plugin_venn-0.5.dist-info/WHEEL
sourmash_plugin_venn-0.5.dist-info/top_level.txt
sourmash_plugin_venn-0.5.dist-info/RECORD
