Metadata-Version: 2.1
Name: sourmash_plugin_venn
Version: 0.5
Summary: sourmash plugin to build venn diagrams - DEPRECATED. Use 'sourmash_plugin_betterplot' instead.
Requires-Python: >=3.8
License-File: LICENSE
Requires-Dist: sourmash<5,>=4.8.0
Requires-Dist: matplotlib
Requires-Dist: matplotlib-venn
